[
    {
        "id": 0,
        "name": "Cheesus",
        "picture": "images/token.jpg",
        "description": "Cheesus is a multichain DeFi analytical tool that helps you find real gems without getting caught in any mousetraps.",
        "price": "0.1 ETH"
    },

    {
        "id": 1,
        "name": "MooMonster",
        "picture": "images/token2.jpeg",
        "description": "Go on an adventure with Moo monster in the new world 'Mooniverse'. Collect and train Moo for battles against others monster.",
        "price": "0.05 ETH"

    },

    {
        "id": 2,
        "name": "Kaizen",
        "picture": "images/kaizen1.png",
        "description": "Kaizen.Finance is a crypto token lifecycle management platform where projects and DAOs can confidently and reliably generate.",
        "price": "0.2 ETH"
    }

]